{
 "name": "筑城者的贝洛伯格",
 "iconPath": "80331805173a643da0bdab71636f622a5e42a42e432a90af6a5255af6f7bb63e",
 "artPath": "18e00298ec945d3975fef04a030129c3a58e1f449b8940ab9024374779c00f68",
 "rarity": 5,
 "relicType": 0,
 "embeddedBaseTypes": {
  "0": {
   "id": 0,
   "iconPath": "6d40bc2fc8f47bd0508d44c359f0091c1c74bbf50e758eafac87e6944f94d261",
   "color": "#FFFFFF",
   "name": "",
   "rarity": 0
  },
  "1": {
   "id": 1,
   "iconPath": "4ecdc8ee012ef343aff72aa68c82787777a1ea73152e6caf1bb99b345a2372cc",
   "color": "#FFFFFF",
   "name": "头部",
   "rarity": 0
  },
  "2": {
   "id": 2,
   "iconPath": "17079e7e6bfc3452cc8cb81d5a9ac6fc0b5e0bb4c3c76cadf39cdb67c3c693c5",
   "color": "#FFFFFF",
   "name": "手部",
   "rarity": 0
  },
  "3": {
   "id": 3,
   "iconPath": "a6c9ef56cae6d9c4347924905d5fdf2305a61d6435c9aeaf532380b3ba7e1338",
   "color": "#FFFFFF",
   "name": "躯干",
   "rarity": 0
  },
  "4": {
   "id": 4,
   "iconPath": "de02abec36b454ef7602c2e918d84eba4774feccd1f9c8c8c7a26091e159f96f",
   "color": "#FFFFFF",
   "name": "脚部",
   "rarity": 0
  },
  "5": {
   "id": 5,
   "iconPath": "dc49142bdd9876527085b02af915e6079a28a204412f8bd755b42f4b646dbf53",
   "color": "#FFFFFF",
   "name": "位面球",
   "rarity": 0
  },
  "6": {
   "id": 6,
   "iconPath": "e5fc490c45f56553c2310bf4420d72150c67abffa504b72571b7e0a93a7adf8e",
   "color": "#FFFFFF",
   "name": "连结绳",
   "rarity": 0
  }
 },
 "skills": [
  {
   "useNum": 2,
   "desc": "使装备者的防御力提高<nobr>#1[i]%</nobr>。当装备者的效果命中大于等于<nobr>#2[i]%</nobr>时，防御力额外提高<nobr>#3[i]%</nobr>。",
   "params": [
    0.15,
    0.5,
    0.15
   ]
  }
 ],
 "pieces": {
  "5": {
   "name": "贝洛伯格的存护堡垒",
   "type": 0,
   "maxRarity": 5,
   "iconPath": "602e40aaf2113b67c63c64c642116983a643e1b32040b06ebd3ec6d7eedb0afb",
   "baseTypeText": "位面球",
   "loreTitle": "贝洛伯格的存护堡垒",
   "miniLore": "位面封装的是贝洛伯格行政区最常见的风景：永冬铭碑。人们从这里路过，感受到来自遥远而温暖的目光守护着他们。",
   "lore": "几千年前，彼时的雅利洛-Ⅵ拥有四季如春的气候与令人嫉妒的海洋环境。<br /><br />林中缀满硕果，潮汐送来湿润暖意，美酒如甘泉般可随手掬取、人人痛饮。当地的居民极富进取心与活力，修建了道路、城市、海边的别墅以及精美的宫殿。富足滋润的生活似乎总是从晨曦的一杯咖啡开始，到暮色的一杯麦芽酿结束。<br /><br />随后星轨连通了雅利洛-Ⅵ的世界，为这里带来了星间贸易和天外科技。<br /><br />一开始，异界的访客们为追寻地髓矿石而来，这些晶莹剔透的矿物蕴藏着驱动工业的血液，琥珀色的反射倒映出存护的光彩；再后来，异界的访客们为长住久安的生活而来，它的海湾、棕榈树、节奏轻快的乐曲，适合任何疲惫的旅客寻求归宿——人们相信假以时日，这颗气候湿润的星球必将如同其他耀目明星一般在银河闪烁。<br /><br />约摸一千年前，一枚星核划过天际，坠落在这个世界上。<br /><br />随即，整个星球的命运急转直下，如同荒诞的闹剧。暴戾的毁灭军团从天而降，滔天的战火此起彼伏。筑城者们构筑起城墙与战线，百米巨像峨然耸立与龙形巨兽角力——紧接着，毫无征兆的寒潮突然出现，凛冽的风暴不分敌我，吞没了一切，整颗星球万籁俱寂…看不见的巨大空间屏障遮覆了堡垒城市，就像寒夜里怀中护住的烛火，文明因此延续。<br /><br />再后来，这座城市被称为贝洛伯格。",
   "rarityData": {
    "2": {
     "rarity": 2,
     "maxLevel": 6,
     "mainAffixes": [
      {
       "propertyName": "生命值",
       "propertyIconPath": "58021be84b486be322a79b327175328186db239a32bd8880315bddfd1470e8a6",
       "isPercent": true,
       "baseValue": 0.027648,
       "levelAdd": 0.009677,
       "stepValue": 0,
       "maxStep": 0
      },
      {
       "propertyName": "攻击力",
       "propertyIconPath": "133ec725c4ee3c0b046da6e56eab2357dda08baf497ea688c317462fb0b93068",
       "isPercent": true,
       "baseValue": 0.027648,
       "levelAdd": 0.009677,
       "stepValue": 0,
       "maxStep": 0
      },
      {
       "propertyName": "防御力",
       "propertyIconPath": "b0aad49714e2daa2922e1c404f67807aa9b69978ddfc922b721ce5effed76d26",
       "isPercent": true,
       "baseValue": 0.034560002,
       "levelAdd": 0.012096001,
       "stepValue": 0,
       "maxStep": 0
      },
      {
       "propertyName": "<span style=\"color:#FFFFFF;\">物理</span>属性伤害提高",
       "propertyIconPath": "757e9735b4fc38499cd7df3f914ef78bb61c21c6f4f595817c66ce4b8f549a6f",
       "isPercent": true,
       "baseValue": 0.024883,
       "levelAdd": 0.008709,
       "stepValue": 0,
       "maxStep": 0
      },
      {
       "propertyName": "<span style=\"color:#F84F36;\">火</span>属性伤害提高",
       "propertyIconPath": "a043a174c8ca7c065ea3c16f99b8ee5b4e70f8c994ed73f29a6204c5f02b409b",
       "isPercent": true,
       "baseValue": 0.024883,
       "levelAdd": 0.008709,
       "stepValue": 0,
       "maxStep": 0
      },
      {
       "propertyName": "<span style=\"color:#47C7FD;\">冰</span>属性伤害提高",
       "propertyIconPath": "30e53905e606abc915cd27cdc42170fc4a8bae2e767f6404e2ba82c80f097b2c",
       "isPercent": true,
       "baseValue": 0.024883,
       "levelAdd": 0.008709,
       "stepValue": 0,
       "maxStep": 0
      },
      {
       "propertyName": "<span style=\"color:#c75de2;\">雷</span>属性伤害提高",
       "propertyIconPath": "ea3212d27d270763b333f348ce2d779103723c83c7a58f09b9c7d2ec6b88ae2d",
       "isPercent": true,
       "baseValue": 0.024883,
       "levelAdd": 0.008709,
       "stepValue": 0,
       "maxStep": 0
      },
      {
       "propertyName": "<span style=\"color:#00FF9C;\">风</span>属性伤害提高",
       "propertyIconPath": "abe12be8cc36732f87619d6e96c92315c0bf5e1c3b63c387cc27e1ab8c8df147",
       "isPercent": true,
       "baseValue": 0.024883,
       "levelAdd": 0.008709,
       "stepValue": 0,
       "maxStep": 0
      },
      {
       "propertyName": "<span style=\"color:#7788ff;\">量子</span>属性伤害提高",
       "propertyIconPath": "74c2e3b79f153375fe4320046a2e2f8eb5fe7fe63c0b3e3c3195696860ac45dc",
       "isPercent": true,
       "baseValue": 0.024883,
       "levelAdd": 0.008709,
       "stepValue": 0,
       "maxStep": 0
      },
      {
       "propertyName": "<span style=\"color:#F4D258;\">虚数</span>属性伤害提高",
       "propertyIconPath": "ec20df586f9edfb73eb4a41af05258fada5d1887be2645f45e3d71466a22bd9a",
       "isPercent": true,
       "baseValue": 0.024883,
       "levelAdd": 0.008709,
       "stepValue": 0,
       "maxStep": 0
      }
     ],
     "subAffixes": [
      {
       "propertyName": "生命值",
       "propertyIconPath": "58021be84b486be322a79b327175328186db239a32bd8880315bddfd1470e8a6",
       "isPercent": false,
       "baseValue": 13.548016,
       "levelAdd": 13.548016,
       "stepValue": 1.693502,
       "maxStep": 2
      },
      {
       "propertyName": "攻击力",
       "propertyIconPath": "133ec725c4ee3c0b046da6e56eab2357dda08baf497ea688c317462fb0b93068",
       "isPercent": false,
       "baseValue": 6.774008,
       "levelAdd": 6.774008,
       "stepValue": 0.846751,
       "maxStep": 2
      },
      {
       "propertyName": "防御力",
       "propertyIconPath": "b0aad49714e2daa2922e1c404f67807aa9b69978ddfc922b721ce5effed76d26",
       "isPercent": false,
       "baseValue": 6.774008,
       "levelAdd": 6.774008,
       "stepValue": 0.846751,
       "maxStep": 2
      },
      {
       "propertyName": "生命值",
       "propertyIconPath": "58021be84b486be322a79b327175328186db239a32bd8880315bddfd1470e8a6",
       "isPercent": true,
       "baseValue": 0.013824001,
       "levelAdd": 0.013824001,
       "stepValue": 0.0017280006,
       "maxStep": 2
      },
      {
       "propertyName": "攻击力",
       "propertyIconPath": "133ec725c4ee3c0b046da6e56eab2357dda08baf497ea688c317462fb0b93068",
       "isPercent": true,
       "baseValue": 0.013824001,
       "levelAdd": 0.013824001,
       "stepValue": 0.0017280006,
       "maxStep": 2
      },
      {
       "propertyName": "防御力",
       "propertyIconPath": "b0aad49714e2daa2922e1c404f67807aa9b69978ddfc922b721ce5effed76d26",
       "isPercent": true,
       "baseValue": 0.017280001,
       "levelAdd": 0.017280001,
       "stepValue": 0.0021600004,
       "maxStep": 2
      },
      {
       "propertyName": "速度",
       "propertyIconPath": "5f33a7516d62d6240538ebf9eef7aabde16d97f27eb53e90ae2cf6eef8168feb",
       "isPercent": false,
       "baseValue": 1,
       "levelAdd": 1,
       "stepValue": 0.1,
       "maxStep": 2
      },
      {
       "propertyName": "暴击率",
       "propertyIconPath": "32af0a785a531bcab9fbe86da7c2f559478bf02bfe8a77d6b539c5702a1a64fb",
       "isPercent": true,
       "baseValue": 0.010368001,
       "levelAdd": 0.010368001,
       "stepValue": 0.0012960008,
       "maxStep": 2
      },
      {
       "propertyName": "暴击伤害",
       "propertyIconPath": "5550e862892998113c65d250603fc60e7a786c520ef82a80f06bd953442418c8",
       "isPercent": true,
       "baseValue": 0.020736001,
       "levelAdd": 0.020736001,
       "stepValue": 0.0025920009,
       "maxStep": 2
      },
      {
       "propertyName": "效果命中",
       "propertyIconPath": "8198085dc42c26a3e3ce48d55bf1b763c6472ac6251fb2533c710f48ab4a4b46",
       "isPercent": true,
       "baseValue": 0.013824001,
       "levelAdd": 0.013824001,
       "stepValue": 0.0017280006,
       "maxStep": 2
      },
      {
       "propertyName": "效果抵抗",
       "propertyIconPath": "1663e14dca8f4e42f151ff8d408f9a449e11fe2cacfbb98276eca60c1abafa24",
       "isPercent": true,
       "baseValue": 0.013824001,
       "levelAdd": 0.013824001,
       "stepValue": 0.0017280006,
       "maxStep": 2
      },
      {
       "propertyName": "击破特攻",
       "propertyIconPath": "757dc56c4923c3e9429fa51fd3d4fa8349581723a44782b0143257fd415bd976",
       "isPercent": true,
       "baseValue": 0.020736001,
       "levelAdd": 0.020736001,
       "stepValue": 0.0025920009,
       "maxStep": 2
      }
     ]
    },
    "3": {
     "rarity": 3,
     "maxLevel": 9,
     "mainAffixes": [
      {
       "propertyName": "生命值",
       "propertyIconPath": "58021be84b486be322a79b327175328186db239a32bd8880315bddfd1470e8a6",
       "isPercent": true,
       "baseValue": 0.041472,
       "levelAdd": 0.014515,
       "stepValue": 0,
       "maxStep": 0
      },
      {
       "propertyName": "攻击力",
       "propertyIconPath": "133ec725c4ee3c0b046da6e56eab2357dda08baf497ea688c317462fb0b93068",
       "isPercent": true,
       "baseValue": 0.041472,
       "levelAdd": 0.014515,
       "stepValue": 0,
       "maxStep": 0
      },
      {
       "propertyName": "防御力",
       "propertyIconPath": "b0aad49714e2daa2922e1c404f67807aa9b69978ddfc922b721ce5effed76d26",
       "isPercent": true,
       "baseValue": 0.05184,
       "levelAdd": 0.018144,
       "stepValue": 0,
       "maxStep": 0
      },
      {
       "propertyName": "<span style=\"color:#FFFFFF;\">物理</span>属性伤害提高",
       "propertyIconPath": "757e9735b4fc38499cd7df3f914ef78bb61c21c6f4f595817c66ce4b8f549a6f",
       "isPercent": true,
       "baseValue": 0.037325,
       "levelAdd": 0.013064001,
       "stepValue": 0,
       "maxStep": 0
      },
      {
       "propertyName": "<span style=\"color:#F84F36;\">火</span>属性伤害提高",
       "propertyIconPath": "a043a174c8ca7c065ea3c16f99b8ee5b4e70f8c994ed73f29a6204c5f02b409b",
       "isPercent": true,
       "baseValue": 0.037325,
       "levelAdd": 0.013064001,
       "stepValue": 0,
       "maxStep": 0
      },
      {
       "propertyName": "<span style=\"color:#47C7FD;\">冰</span>属性伤害提高",
       "propertyIconPath": "30e53905e606abc915cd27cdc42170fc4a8bae2e767f6404e2ba82c80f097b2c",
       "isPercent": true,
       "baseValue": 0.037325,
       "levelAdd": 0.013064001,
       "stepValue": 0,
       "maxStep": 0
      },
      {
       "propertyName": "<span style=\"color:#c75de2;\">雷</span>属性伤害提高",
       "propertyIconPath": "ea3212d27d270763b333f348ce2d779103723c83c7a58f09b9c7d2ec6b88ae2d",
       "isPercent": true,
       "baseValue": 0.037325,
       "levelAdd": 0.013064001,
       "stepValue": 0,
       "maxStep": 0
      },
      {
       "propertyName": "<span style=\"color:#00FF9C;\">风</span>属性伤害提高",
       "propertyIconPath": "abe12be8cc36732f87619d6e96c92315c0bf5e1c3b63c387cc27e1ab8c8df147",
       "isPercent": true,
       "baseValue": 0.037325,
       "levelAdd": 0.013064001,
       "stepValue": 0,
       "maxStep": 0
      },
      {
       "propertyName": "<span style=\"color:#7788ff;\">量子</span>属性伤害提高",
       "propertyIconPath": "74c2e3b79f153375fe4320046a2e2f8eb5fe7fe63c0b3e3c3195696860ac45dc",
       "isPercent": true,
       "baseValue": 0.037325,
       "levelAdd": 0.013064001,
       "stepValue": 0,
       "maxStep": 0
      },
      {
       "propertyName": "<span style=\"color:#F4D258;\">虚数</span>属性伤害提高",
       "propertyIconPath": "ec20df586f9edfb73eb4a41af05258fada5d1887be2645f45e3d71466a22bd9a",
       "isPercent": true,
       "baseValue": 0.037325,
       "levelAdd": 0.013064001,
       "stepValue": 0,
       "maxStep": 0
      }
     ],
     "subAffixes": [
      {
       "propertyName": "生命值",
       "propertyIconPath": "58021be84b486be322a79b327175328186db239a32bd8880315bddfd1470e8a6",
       "isPercent": false,
       "baseValue": 20.322023,
       "levelAdd": 20.322023,
       "stepValue": 2.540253,
       "maxStep": 2
      },
      {
       "propertyName": "攻击力",
       "propertyIconPath": "133ec725c4ee3c0b046da6e56eab2357dda08baf497ea688c317462fb0b93068",
       "isPercent": false,
       "baseValue": 10.161012,
       "levelAdd": 10.161012,
       "stepValue": 1.270126,
       "maxStep": 2
      },
      {
       "propertyName": "防御力",
       "propertyIconPath": "b0aad49714e2daa2922e1c404f67807aa9b69978ddfc922b721ce5effed76d26",
       "isPercent": false,
       "baseValue": 10.161012,
       "levelAdd": 10.161012,
       "stepValue": 1.270126,
       "maxStep": 2
      },
      {
       "propertyName": "生命值",
       "propertyIconPath": "58021be84b486be322a79b327175328186db239a32bd8880315bddfd1470e8a6",
       "isPercent": true,
       "baseValue": 0.020736001,
       "levelAdd": 0.020736001,
       "stepValue": 0.0025920009,
       "maxStep": 2
      },
      {
       "propertyName": "攻击力",
       "propertyIconPath": "133ec725c4ee3c0b046da6e56eab2357dda08baf497ea688c317462fb0b93068",
       "isPercent": true,
       "baseValue": 0.020736001,
       "levelAdd": 0.020736001,
       "stepValue": 0.0025920009,
       "maxStep": 2
      },
      {
       "propertyName": "防御力",
       "propertyIconPath": "b0aad49714e2daa2922e1c404f67807aa9b69978ddfc922b721ce5effed76d26",
       "isPercent": true,
       "baseValue": 0.02592,
       "levelAdd": 0.02592,
       "stepValue": 0.0032400002,
       "maxStep": 2
      },
      {
       "propertyName": "速度",
       "propertyIconPath": "5f33a7516d62d6240538ebf9eef7aabde16d97f27eb53e90ae2cf6eef8168feb",
       "isPercent": false,
       "baseValue": 1.2,
       "levelAdd": 1.2,
       "stepValue": 0.1,
       "maxStep": 2
      },
      {
       "propertyName": "暴击率",
       "propertyIconPath": "32af0a785a531bcab9fbe86da7c2f559478bf02bfe8a77d6b539c5702a1a64fb",
       "isPercent": true,
       "baseValue": 0.015552,
       "levelAdd": 0.015552,
       "stepValue": 0.0019440008,
       "maxStep": 2
      },
      {
       "propertyName": "暴击伤害",
       "propertyIconPath": "5550e862892998113c65d250603fc60e7a786c520ef82a80f06bd953442418c8",
       "isPercent": true,
       "baseValue": 0.031104,
       "levelAdd": 0.031104,
       "stepValue": 0.003888001,
       "maxStep": 2
      },
      {
       "propertyName": "效果命中",
       "propertyIconPath": "8198085dc42c26a3e3ce48d55bf1b763c6472ac6251fb2533c710f48ab4a4b46",
       "isPercent": true,
       "baseValue": 0.020736001,
       "levelAdd": 0.020736001,
       "stepValue": 0.0025920009,
       "maxStep": 2
      },
      {
       "propertyName": "效果抵抗",
       "propertyIconPath": "1663e14dca8f4e42f151ff8d408f9a449e11fe2cacfbb98276eca60c1abafa24",
       "isPercent": true,
       "baseValue": 0.020736001,
       "levelAdd": 0.020736001,
       "stepValue": 0.0025920009,
       "maxStep": 2
      },
      {
       "propertyName": "击破特攻",
       "propertyIconPath": "757dc56c4923c3e9429fa51fd3d4fa8349581723a44782b0143257fd415bd976",
       "isPercent": true,
       "baseValue": 0.031104,
       "levelAdd": 0.031104,
       "stepValue": 0.003888001,
       "maxStep": 2
      }
     ]
    },
    "4": {
     "rarity": 4,
     "maxLevel": 12,
     "mainAffixes": [
      {
       "propertyName": "生命值",
       "propertyIconPath": "58021be84b486be322a79b327175328186db239a32bd8880315bddfd1470e8a6",
       "isPercent": true,
       "baseValue": 0.055296,
       "levelAdd": 0.019354,
       "stepValue": 0,
       "maxStep": 0
      },
      {
       "propertyName": "攻击力",
       "propertyIconPath": "133ec725c4ee3c0b046da6e56eab2357dda08baf497ea688c317462fb0b93068",
       "isPercent": true,
       "baseValue": 0.055296,
       "levelAdd": 0.019354,
       "stepValue": 0,
       "maxStep": 0
      },
      {
       "propertyName": "防御力",
       "propertyIconPath": "b0aad49714e2daa2922e1c404f67807aa9b69978ddfc922b721ce5effed76d26",
       "isPercent": true,
       "baseValue": 0.06912,
       "levelAdd": 0.024192,
       "stepValue": 0,
       "maxStep": 0
      },
      {
       "propertyName": "<span style=\"color:#FFFFFF;\">物理</span>属性伤害提高",
       "propertyIconPath": "757e9735b4fc38499cd7df3f914ef78bb61c21c6f4f595817c66ce4b8f549a6f",
       "isPercent": true,
       "baseValue": 0.049766,
       "levelAdd": 0.017418,
       "stepValue": 0,
       "maxStep": 0
      },
      {
       "propertyName": "<span style=\"color:#F84F36;\">火</span>属性伤害提高",
       "propertyIconPath": "a043a174c8ca7c065ea3c16f99b8ee5b4e70f8c994ed73f29a6204c5f02b409b",
       "isPercent": true,
       "baseValue": 0.049766,
       "levelAdd": 0.017418,
       "stepValue": 0,
       "maxStep": 0
      },
      {
       "propertyName": "<span style=\"color:#47C7FD;\">冰</span>属性伤害提高",
       "propertyIconPath": "30e53905e606abc915cd27cdc42170fc4a8bae2e767f6404e2ba82c80f097b2c",
       "isPercent": true,
       "baseValue": 0.049766,
       "levelAdd": 0.017418,
       "stepValue": 0,
       "maxStep": 0
      },
      {
       "propertyName": "<span style=\"color:#c75de2;\">雷</span>属性伤害提高",
       "propertyIconPath": "ea3212d27d270763b333f348ce2d779103723c83c7a58f09b9c7d2ec6b88ae2d",
       "isPercent": true,
       "baseValue": 0.049766,
       "levelAdd": 0.017418,
       "stepValue": 0,
       "maxStep": 0
      },
      {
       "propertyName": "<span style=\"color:#00FF9C;\">风</span>属性伤害提高",
       "propertyIconPath": "abe12be8cc36732f87619d6e96c92315c0bf5e1c3b63c387cc27e1ab8c8df147",
       "isPercent": true,
       "baseValue": 0.049766,
       "levelAdd": 0.017418,
       "stepValue": 0,
       "maxStep": 0
      },
      {
       "propertyName": "<span style=\"color:#7788ff;\">量子</span>属性伤害提高",
       "propertyIconPath": "74c2e3b79f153375fe4320046a2e2f8eb5fe7fe63c0b3e3c3195696860ac45dc",
       "isPercent": true,
       "baseValue": 0.049766,
       "levelAdd": 0.017418,
       "stepValue": 0,
       "maxStep": 0
      },
      {
       "propertyName": "<span style=\"color:#F4D258;\">虚数</span>属性伤害提高",
       "propertyIconPath": "ec20df586f9edfb73eb4a41af05258fada5d1887be2645f45e3d71466a22bd9a",
       "isPercent": true,
       "baseValue": 0.049766,
       "levelAdd": 0.017418,
       "stepValue": 0,
       "maxStep": 0
      }
     ],
     "subAffixes": [
      {
       "propertyName": "生命值",
       "propertyIconPath": "58021be84b486be322a79b327175328186db239a32bd8880315bddfd1470e8a6",
       "isPercent": false,
       "baseValue": 27.096031,
       "levelAdd": 27.096031,
       "stepValue": 3.387004,
       "maxStep": 2
      },
      {
       "propertyName": "攻击力",
       "propertyIconPath": "133ec725c4ee3c0b046da6e56eab2357dda08baf497ea688c317462fb0b93068",
       "isPercent": false,
       "baseValue": 13.548016,
       "levelAdd": 13.548016,
       "stepValue": 1.693502,
       "maxStep": 2
      },
      {
       "propertyName": "防御力",
       "propertyIconPath": "b0aad49714e2daa2922e1c404f67807aa9b69978ddfc922b721ce5effed76d26",
       "isPercent": false,
       "baseValue": 13.548016,
       "levelAdd": 13.548016,
       "stepValue": 1.693502,
       "maxStep": 2
      },
      {
       "propertyName": "生命值",
       "propertyIconPath": "58021be84b486be322a79b327175328186db239a32bd8880315bddfd1470e8a6",
       "isPercent": true,
       "baseValue": 0.027648,
       "levelAdd": 0.027648,
       "stepValue": 0.0034560005,
       "maxStep": 2
      },
      {
       "propertyName": "攻击力",
       "propertyIconPath": "133ec725c4ee3c0b046da6e56eab2357dda08baf497ea688c317462fb0b93068",
       "isPercent": true,
       "baseValue": 0.027648,
       "levelAdd": 0.027648,
       "stepValue": 0.0034560005,
       "maxStep": 2
      },
      {
       "propertyName": "防御力",
       "propertyIconPath": "b0aad49714e2daa2922e1c404f67807aa9b69978ddfc922b721ce5effed76d26",
       "isPercent": true,
       "baseValue": 0.034560002,
       "levelAdd": 0.034560002,
       "stepValue": 0.0043200003,
       "maxStep": 2
      },
      {
       "propertyName": "速度",
       "propertyIconPath": "5f33a7516d62d6240538ebf9eef7aabde16d97f27eb53e90ae2cf6eef8168feb",
       "isPercent": false,
       "baseValue": 1.6,
       "levelAdd": 1.6,
       "stepValue": 0.2,
       "maxStep": 2
      },
      {
       "propertyName": "暴击率",
       "propertyIconPath": "32af0a785a531bcab9fbe86da7c2f559478bf02bfe8a77d6b539c5702a1a64fb",
       "isPercent": true,
       "baseValue": 0.020736001,
       "levelAdd": 0.020736001,
       "stepValue": 0.0025920009,
       "maxStep": 2
      },
      {
       "propertyName": "暴击伤害",
       "propertyIconPath": "5550e862892998113c65d250603fc60e7a786c520ef82a80f06bd953442418c8",
       "isPercent": true,
       "baseValue": 0.041472,
       "levelAdd": 0.041472,
       "stepValue": 0.0051840004,
       "maxStep": 2
      },
      {
       "propertyName": "效果命中",
       "propertyIconPath": "8198085dc42c26a3e3ce48d55bf1b763c6472ac6251fb2533c710f48ab4a4b46",
       "isPercent": true,
       "baseValue": 0.027648,
       "levelAdd": 0.027648,
       "stepValue": 0.0034560005,
       "maxStep": 2
      },
      {
       "propertyName": "效果抵抗",
       "propertyIconPath": "1663e14dca8f4e42f151ff8d408f9a449e11fe2cacfbb98276eca60c1abafa24",
       "isPercent": true,
       "baseValue": 0.027648,
       "levelAdd": 0.027648,
       "stepValue": 0.0034560005,
       "maxStep": 2
      },
      {
       "propertyName": "击破特攻",
       "propertyIconPath": "757dc56c4923c3e9429fa51fd3d4fa8349581723a44782b0143257fd415bd976",
       "isPercent": true,
       "baseValue": 0.041472,
       "levelAdd": 0.041472,
       "stepValue": 0.0051840004,
       "maxStep": 2
      }
     ]
    },
    "5": {
     "rarity": 5,
     "maxLevel": 15,
     "mainAffixes": [
      {
       "propertyName": "生命值",
       "propertyIconPath": "58021be84b486be322a79b327175328186db239a32bd8880315bddfd1470e8a6",
       "isPercent": true,
       "baseValue": 0.06912,
       "levelAdd": 0.024192,
       "stepValue": 0,
       "maxStep": 0
      },
      {
       "propertyName": "攻击力",
       "propertyIconPath": "133ec725c4ee3c0b046da6e56eab2357dda08baf497ea688c317462fb0b93068",
       "isPercent": true,
       "baseValue": 0.06912,
       "levelAdd": 0.024192,
       "stepValue": 0,
       "maxStep": 0
      },
      {
       "propertyName": "防御力",
       "propertyIconPath": "b0aad49714e2daa2922e1c404f67807aa9b69978ddfc922b721ce5effed76d26",
       "isPercent": true,
       "baseValue": 0.0864,
       "levelAdd": 0.030240001,
       "stepValue": 0,
       "maxStep": 0
      },
      {
       "propertyName": "<span style=\"color:#FFFFFF;\">物理</span>属性伤害提高",
       "propertyIconPath": "757e9735b4fc38499cd7df3f914ef78bb61c21c6f4f595817c66ce4b8f549a6f",
       "isPercent": true,
       "baseValue": 0.062208,
       "levelAdd": 0.021773001,
       "stepValue": 0,
       "maxStep": 0
      },
      {
       "propertyName": "<span style=\"color:#F84F36;\">火</span>属性伤害提高",
       "propertyIconPath": "a043a174c8ca7c065ea3c16f99b8ee5b4e70f8c994ed73f29a6204c5f02b409b",
       "isPercent": true,
       "baseValue": 0.062208,
       "levelAdd": 0.021773001,
       "stepValue": 0,
       "maxStep": 0
      },
      {
       "propertyName": "<span style=\"color:#47C7FD;\">冰</span>属性伤害提高",
       "propertyIconPath": "30e53905e606abc915cd27cdc42170fc4a8bae2e767f6404e2ba82c80f097b2c",
       "isPercent": true,
       "baseValue": 0.062208,
       "levelAdd": 0.021773001,
       "stepValue": 0,
       "maxStep": 0
      },
      {
       "propertyName": "<span style=\"color:#c75de2;\">雷</span>属性伤害提高",
       "propertyIconPath": "ea3212d27d270763b333f348ce2d779103723c83c7a58f09b9c7d2ec6b88ae2d",
       "isPercent": true,
       "baseValue": 0.062208,
       "levelAdd": 0.021773001,
       "stepValue": 0,
       "maxStep": 0
      },
      {
       "propertyName": "<span style=\"color:#00FF9C;\">风</span>属性伤害提高",
       "propertyIconPath": "abe12be8cc36732f87619d6e96c92315c0bf5e1c3b63c387cc27e1ab8c8df147",
       "isPercent": true,
       "baseValue": 0.062208,
       "levelAdd": 0.021773001,
       "stepValue": 0,
       "maxStep": 0
      },
      {
       "propertyName": "<span style=\"color:#7788ff;\">量子</span>属性伤害提高",
       "propertyIconPath": "74c2e3b79f153375fe4320046a2e2f8eb5fe7fe63c0b3e3c3195696860ac45dc",
       "isPercent": true,
       "baseValue": 0.062208,
       "levelAdd": 0.021773001,
       "stepValue": 0,
       "maxStep": 0
      },
      {
       "propertyName": "<span style=\"color:#F4D258;\">虚数</span>属性伤害提高",
       "propertyIconPath": "ec20df586f9edfb73eb4a41af05258fada5d1887be2645f45e3d71466a22bd9a",
       "isPercent": true,
       "baseValue": 0.062208,
       "levelAdd": 0.021773001,
       "stepValue": 0,
       "maxStep": 0
      }
     ],
     "subAffixes": [
      {
       "propertyName": "生命值",
       "propertyIconPath": "58021be84b486be322a79b327175328186db239a32bd8880315bddfd1470e8a6",
       "isPercent": false,
       "baseValue": 33.87004,
       "levelAdd": 33.87004,
       "stepValue": 4.233755,
       "maxStep": 2
      },
      {
       "propertyName": "攻击力",
       "propertyIconPath": "133ec725c4ee3c0b046da6e56eab2357dda08baf497ea688c317462fb0b93068",
       "isPercent": false,
       "baseValue": 16.935019,
       "levelAdd": 16.935019,
       "stepValue": 2.116877,
       "maxStep": 2
      },
      {
       "propertyName": "防御力",
       "propertyIconPath": "b0aad49714e2daa2922e1c404f67807aa9b69978ddfc922b721ce5effed76d26",
       "isPercent": false,
       "baseValue": 16.935019,
       "levelAdd": 16.935019,
       "stepValue": 2.116877,
       "maxStep": 2
      },
      {
       "propertyName": "生命值",
       "propertyIconPath": "58021be84b486be322a79b327175328186db239a32bd8880315bddfd1470e8a6",
       "isPercent": true,
       "baseValue": 0.034560002,
       "levelAdd": 0.034560002,
       "stepValue": 0.0043200003,
       "maxStep": 2
      },
      {
       "propertyName": "攻击力",
       "propertyIconPath": "133ec725c4ee3c0b046da6e56eab2357dda08baf497ea688c317462fb0b93068",
       "isPercent": true,
       "baseValue": 0.034560002,
       "levelAdd": 0.034560002,
       "stepValue": 0.0043200003,
       "maxStep": 2
      },
      {
       "propertyName": "防御力",
       "propertyIconPath": "b0aad49714e2daa2922e1c404f67807aa9b69978ddfc922b721ce5effed76d26",
       "isPercent": true,
       "baseValue": 0.0432,
       "levelAdd": 0.0432,
       "stepValue": 0.0054,
       "maxStep": 2
      },
      {
       "propertyName": "速度",
       "propertyIconPath": "5f33a7516d62d6240538ebf9eef7aabde16d97f27eb53e90ae2cf6eef8168feb",
       "isPercent": false,
       "baseValue": 2,
       "levelAdd": 2,
       "stepValue": 0.3,
       "maxStep": 2
      },
      {
       "propertyName": "暴击率",
       "propertyIconPath": "32af0a785a531bcab9fbe86da7c2f559478bf02bfe8a77d6b539c5702a1a64fb",
       "isPercent": true,
       "baseValue": 0.02592,
       "levelAdd": 0.02592,
       "stepValue": 0.0032400002,
       "maxStep": 2
      },
      {
       "propertyName": "暴击伤害",
       "propertyIconPath": "5550e862892998113c65d250603fc60e7a786c520ef82a80f06bd953442418c8",
       "isPercent": true,
       "baseValue": 0.05184,
       "levelAdd": 0.05184,
       "stepValue": 0.0064800004,
       "maxStep": 2
      },
      {
       "propertyName": "效果命中",
       "propertyIconPath": "8198085dc42c26a3e3ce48d55bf1b763c6472ac6251fb2533c710f48ab4a4b46",
       "isPercent": true,
       "baseValue": 0.034560002,
       "levelAdd": 0.034560002,
       "stepValue": 0.0043200003,
       "maxStep": 2
      },
      {
       "propertyName": "效果抵抗",
       "propertyIconPath": "1663e14dca8f4e42f151ff8d408f9a449e11fe2cacfbb98276eca60c1abafa24",
       "isPercent": true,
       "baseValue": 0.034560002,
       "levelAdd": 0.034560002,
       "stepValue": 0.0043200003,
       "maxStep": 2
      },
      {
       "propertyName": "击破特攻",
       "propertyIconPath": "757dc56c4923c3e9429fa51fd3d4fa8349581723a44782b0143257fd415bd976",
       "isPercent": true,
       "baseValue": 0.05184,
       "levelAdd": 0.05184,
       "stepValue": 0.0064800004,
       "maxStep": 2
      }
     ]
    }
   }
  },
  "6": {
   "name": "贝洛伯格的铁卫防线",
   "type": 0,
   "maxRarity": 5,
   "iconPath": "21bb4d8390311b6429f81758ef4522bf76b1c2ba3be7d2bc76fb2a8b883f55ec",
   "baseTypeText": "连结绳",
   "loreTitle": "贝洛伯格的铁卫防线",
   "miniLore": "贝洛伯格的银鬃铁卫矗立在风雪之中，他们排成一线，等待着前来进犯的天外入侵者。铁卫的意志坚不可摧，铁卫的阵线也绝不后退。",
   "lore": "灾难来临前，筑城者曾对雅利洛-Ⅵ有过美好畅想。<br /><br />筑城者效仿克里珀伟力，铸造出能够改造行星的机械。数百座「造物引擎」吐息烈焰，轰然行于大地，犹如不倦的巨人园丁修葺荒芜的花田。短短几十年，沟壑与丘陵被整为平原与森林，城市星罗棋布耸立于海岸之畔。<br /><br />「毁灭」的预兆降临后，筑城者将机械悉数投入战场，构筑起最初的「铁卫防线」。<br /><br />毁灭的兵卒们如同蹈火的飞萤，紧随星核而至，在地表划下生灵涂炭的轨迹。曾用于「造物」的机械也不得不沦为凶器，在不属于它们的战场上抡动铁拳；最终，耕耘花园的巨人力尽倒下，仿佛一座座文明的墓碑，标记了阵线逐日溃退的历程。<br /><br />退无可退的那一日，铁卫们握紧武器，身后是仅存的家园。<br /><br />寒潮的到来出乎所有的人的意料。天外的怪物与前线的士兵锋刃交错的瞬间，雪线漫涌天际。一片混沌中，贝洛伯格成了世间唯一的灯火。为了扑灭它，为了守护它，双方陷入了漫无止境的厮杀。铁卫们咆哮着阿丽萨•兰德的名字，返身进入风雪深处，再也没有回来。<br /><br />直到暴雪止歇，贝洛伯格的居民战战兢兢地攀上城头远眺。<br /><br />他们见证了最后的「铁卫防线」。",
   "rarityData": {
    "2": {
     "rarity": 2,
     "maxLevel": 6,
     "mainAffixes": [
      {
       "propertyName": "击破特攻",
       "propertyIconPath": "757dc56c4923c3e9429fa51fd3d4fa8349581723a44782b0143257fd415bd976",
       "isPercent": true,
       "baseValue": 0.041472,
       "levelAdd": 0.014515,
       "stepValue": 0,
       "maxStep": 0
      },
      {
       "propertyName": "能量恢复效率",
       "propertyIconPath": "c89104a223ee62a5861a61c20cdb1e42c79d7f6f1767a5dfc5a94f5edbb145ec",
       "isPercent": true,
       "baseValue": 0.012442,
       "levelAdd": 0.0043550003,
       "stepValue": 0,
       "maxStep": 0
      },
      {
       "propertyName": "生命值",
       "propertyIconPath": "58021be84b486be322a79b327175328186db239a32bd8880315bddfd1470e8a6",
       "isPercent": true,
       "baseValue": 0.027648,
       "levelAdd": 0.009677,
       "stepValue": 0,
       "maxStep": 0
      },
      {
       "propertyName": "攻击力",
       "propertyIconPath": "133ec725c4ee3c0b046da6e56eab2357dda08baf497ea688c317462fb0b93068",
       "isPercent": true,
       "baseValue": 0.027648,
       "levelAdd": 0.009677,
       "stepValue": 0,
       "maxStep": 0
      },
      {
       "propertyName": "防御力",
       "propertyIconPath": "b0aad49714e2daa2922e1c404f67807aa9b69978ddfc922b721ce5effed76d26",
       "isPercent": true,
       "baseValue": 0.034560002,
       "levelAdd": 0.012096001,
       "stepValue": 0,
       "maxStep": 0
      }
     ],
     "subAffixes": [
      {
       "propertyName": "生命值",
       "propertyIconPath": "58021be84b486be322a79b327175328186db239a32bd8880315bddfd1470e8a6",
       "isPercent": false,
       "baseValue": 13.548016,
       "levelAdd": 13.548016,
       "stepValue": 1.693502,
       "maxStep": 2
      },
      {
       "propertyName": "攻击力",
       "propertyIconPath": "133ec725c4ee3c0b046da6e56eab2357dda08baf497ea688c317462fb0b93068",
       "isPercent": false,
       "baseValue": 6.774008,
       "levelAdd": 6.774008,
       "stepValue": 0.846751,
       "maxStep": 2
      },
      {
       "propertyName": "防御力",
       "propertyIconPath": "b0aad49714e2daa2922e1c404f67807aa9b69978ddfc922b721ce5effed76d26",
       "isPercent": false,
       "baseValue": 6.774008,
       "levelAdd": 6.774008,
       "stepValue": 0.846751,
       "maxStep": 2
      },
      {
       "propertyName": "生命值",
       "propertyIconPath": "58021be84b486be322a79b327175328186db239a32bd8880315bddfd1470e8a6",
       "isPercent": true,
       "baseValue": 0.013824001,
       "levelAdd": 0.013824001,
       "stepValue": 0.0017280006,
       "maxStep": 2
      },
      {
       "propertyName": "攻击力",
       "propertyIconPath": "133ec725c4ee3c0b046da6e56eab2357dda08baf497ea688c317462fb0b93068",
       "isPercent": true,
       "baseValue": 0.013824001,
       "levelAdd": 0.013824001,
       "stepValue": 0.0017280006,
       "maxStep": 2
      },
      {
       "propertyName": "防御力",
       "propertyIconPath": "b0aad49714e2daa2922e1c404f67807aa9b69978ddfc922b721ce5effed76d26",
       "isPercent": true,
       "baseValue": 0.017280001,
       "levelAdd": 0.017280001,
       "stepValue": 0.0021600004,
       "maxStep": 2
      },
      {
       "propertyName": "速度",
       "propertyIconPath": "5f33a7516d62d6240538ebf9eef7aabde16d97f27eb53e90ae2cf6eef8168feb",
       "isPercent": false,
       "baseValue": 1,
       "levelAdd": 1,
       "stepValue": 0.1,
       "maxStep": 2
      },
      {
       "propertyName": "暴击率",
       "propertyIconPath": "32af0a785a531bcab9fbe86da7c2f559478bf02bfe8a77d6b539c5702a1a64fb",
       "isPercent": true,
       "baseValue": 0.010368001,
       "levelAdd": 0.010368001,
       "stepValue": 0.0012960008,
       "maxStep": 2
      },
      {
       "propertyName": "暴击伤害",
       "propertyIconPath": "5550e862892998113c65d250603fc60e7a786c520ef82a80f06bd953442418c8",
       "isPercent": true,
       "baseValue": 0.020736001,
       "levelAdd": 0.020736001,
       "stepValue": 0.0025920009,
       "maxStep": 2
      },
      {
       "propertyName": "效果命中",
       "propertyIconPath": "8198085dc42c26a3e3ce48d55bf1b763c6472ac6251fb2533c710f48ab4a4b46",
       "isPercent": true,
       "baseValue": 0.013824001,
       "levelAdd": 0.013824001,
       "stepValue": 0.0017280006,
       "maxStep": 2
      },
      {
       "propertyName": "效果抵抗",
       "propertyIconPath": "1663e14dca8f4e42f151ff8d408f9a449e11fe2cacfbb98276eca60c1abafa24",
       "isPercent": true,
       "baseValue": 0.013824001,
       "levelAdd": 0.013824001,
       "stepValue": 0.0017280006,
       "maxStep": 2
      },
      {
       "propertyName": "击破特攻",
       "propertyIconPath": "757dc56c4923c3e9429fa51fd3d4fa8349581723a44782b0143257fd415bd976",
       "isPercent": true,
       "baseValue": 0.020736001,
       "levelAdd": 0.020736001,
       "stepValue": 0.0025920009,
       "maxStep": 2
      }
     ]
    },
    "3": {
     "rarity": 3,
     "maxLevel": 9,
     "mainAffixes": [
      {
       "propertyName": "击破特攻",
       "propertyIconPath": "757dc56c4923c3e9429fa51fd3d4fa8349581723a44782b0143257fd415bd976",
       "isPercent": true,
       "baseValue": 0.062208,
       "levelAdd": 0.021773001,
       "stepValue": 0,
       "maxStep": 0
      },
      {
       "propertyName": "能量恢复效率",
       "propertyIconPath": "c89104a223ee62a5861a61c20cdb1e42c79d7f6f1767a5dfc5a94f5edbb145ec",
       "isPercent": true,
       "baseValue": 0.018662,
       "levelAdd": 0.0065320004,
       "stepValue": 0,
       "maxStep": 0
      },
      {
       "propertyName": "生命值",
       "propertyIconPath": "58021be84b486be322a79b327175328186db239a32bd8880315bddfd1470e8a6",
       "isPercent": true,
       "baseValue": 0.041472,
       "levelAdd": 0.014515,
       "stepValue": 0,
       "maxStep": 0
      },
      {
       "propertyName": "攻击力",
       "propertyIconPath": "133ec725c4ee3c0b046da6e56eab2357dda08baf497ea688c317462fb0b93068",
       "isPercent": true,
       "baseValue": 0.041472,
       "levelAdd": 0.014515,
       "stepValue": 0,
       "maxStep": 0
      },
      {
       "propertyName": "防御力",
       "propertyIconPath": "b0aad49714e2daa2922e1c404f67807aa9b69978ddfc922b721ce5effed76d26",
       "isPercent": true,
       "baseValue": 0.05184,
       "levelAdd": 0.018144,
       "stepValue": 0,
       "maxStep": 0
      }
     ],
     "subAffixes": [
      {
       "propertyName": "生命值",
       "propertyIconPath": "58021be84b486be322a79b327175328186db239a32bd8880315bddfd1470e8a6",
       "isPercent": false,
       "baseValue": 20.322023,
       "levelAdd": 20.322023,
       "stepValue": 2.540253,
       "maxStep": 2
      },
      {
       "propertyName": "攻击力",
       "propertyIconPath": "133ec725c4ee3c0b046da6e56eab2357dda08baf497ea688c317462fb0b93068",
       "isPercent": false,
       "baseValue": 10.161012,
       "levelAdd": 10.161012,
       "stepValue": 1.270126,
       "maxStep": 2
      },
      {
       "propertyName": "防御力",
       "propertyIconPath": "b0aad49714e2daa2922e1c404f67807aa9b69978ddfc922b721ce5effed76d26",
       "isPercent": false,
       "baseValue": 10.161012,
       "levelAdd": 10.161012,
       "stepValue": 1.270126,
       "maxStep": 2
      },
      {
       "propertyName": "生命值",
       "propertyIconPath": "58021be84b486be322a79b327175328186db239a32bd8880315bddfd1470e8a6",
       "isPercent": true,
       "baseValue": 0.020736001,
       "levelAdd": 0.020736001,
       "stepValue": 0.0025920009,
       "maxStep": 2
      },
      {
       "propertyName": "攻击力",
       "propertyIconPath": "133ec725c4ee3c0b046da6e56eab2357dda08baf497ea688c317462fb0b93068",
       "isPercent": true,
       "baseValue": 0.020736001,
       "levelAdd": 0.020736001,
       "stepValue": 0.0025920009,
       "maxStep": 2
      },
      {
       "propertyName": "防御力",
       "propertyIconPath": "b0aad49714e2daa2922e1c404f67807aa9b69978ddfc922b721ce5effed76d26",
       "isPercent": true,
       "baseValue": 0.02592,
       "levelAdd": 0.02592,
       "stepValue": 0.0032400002,
       "maxStep": 2
      },
      {
       "propertyName": "速度",
       "propertyIconPath": "5f33a7516d62d6240538ebf9eef7aabde16d97f27eb53e90ae2cf6eef8168feb",
       "isPercent": false,
       "baseValue": 1.2,
       "levelAdd": 1.2,
       "stepValue": 0.1,
       "maxStep": 2
      },
      {
       "propertyName": "暴击率",
       "propertyIconPath": "32af0a785a531bcab9fbe86da7c2f559478bf02bfe8a77d6b539c5702a1a64fb",
       "isPercent": true,
       "baseValue": 0.015552,
       "levelAdd": 0.015552,
       "stepValue": 0.0019440008,
       "maxStep": 2
      },
      {
       "propertyName": "暴击伤害",
       "propertyIconPath": "5550e862892998113c65d250603fc60e7a786c520ef82a80f06bd953442418c8",
       "isPercent": true,
       "baseValue": 0.031104,
       "levelAdd": 0.031104,
       "stepValue": 0.003888001,
       "maxStep": 2
      },
      {
       "propertyName": "效果命中",
       "propertyIconPath": "8198085dc42c26a3e3ce48d55bf1b763c6472ac6251fb2533c710f48ab4a4b46",
       "isPercent": true,
       "baseValue": 0.020736001,
       "levelAdd": 0.020736001,
       "stepValue": 0.0025920009,
       "maxStep": 2
      },
      {
       "propertyName": "效果抵抗",
       "propertyIconPath": "1663e14dca8f4e42f151ff8d408f9a449e11fe2cacfbb98276eca60c1abafa24",
       "isPercent": true,
       "baseValue": 0.020736001,
       "levelAdd": 0.020736001,
       "stepValue": 0.0025920009,
       "maxStep": 2
      },
      {
       "propertyName": "击破特攻",
       "propertyIconPath": "757dc56c4923c3e9429fa51fd3d4fa8349581723a44782b0143257fd415bd976",
       "isPercent": true,
       "baseValue": 0.031104,
       "levelAdd": 0.031104,
       "stepValue": 0.003888001,
       "maxStep": 2
      }
     ]
    },
    "4": {
     "rarity": 4,
     "maxLevel": 12,
     "mainAffixes": [
      {
       "propertyName": "击破特攻",
       "propertyIconPath": "757dc56c4923c3e9429fa51fd3d4fa8349581723a44782b0143257fd415bd976",
       "isPercent": true,
       "baseValue": 0.082944,
       "levelAdd": 0.029029999,
       "stepValue": 0,
       "maxStep": 0
      },
      {
       "propertyName": "能量恢复效率",
       "propertyIconPath": "c89104a223ee62a5861a61c20cdb1e42c79d7f6f1767a5dfc5a94f5edbb145ec",
       "isPercent": true,
       "baseValue": 0.024883,
       "levelAdd": 0.008709,
       "stepValue": 0,
       "maxStep": 0
      },
      {
       "propertyName": "生命值",
       "propertyIconPath": "58021be84b486be322a79b327175328186db239a32bd8880315bddfd1470e8a6",
       "isPercent": true,
       "baseValue": 0.055296,
       "levelAdd": 0.019354,
       "stepValue": 0,
       "maxStep": 0
      },
      {
       "propertyName": "攻击力",
       "propertyIconPath": "133ec725c4ee3c0b046da6e56eab2357dda08baf497ea688c317462fb0b93068",
       "isPercent": true,
       "baseValue": 0.055296,
       "levelAdd": 0.019354,
       "stepValue": 0,
       "maxStep": 0
      },
      {
       "propertyName": "防御力",
       "propertyIconPath": "b0aad49714e2daa2922e1c404f67807aa9b69978ddfc922b721ce5effed76d26",
       "isPercent": true,
       "baseValue": 0.06912,
       "levelAdd": 0.024192,
       "stepValue": 0,
       "maxStep": 0
      }
     ],
     "subAffixes": [
      {
       "propertyName": "生命值",
       "propertyIconPath": "58021be84b486be322a79b327175328186db239a32bd8880315bddfd1470e8a6",
       "isPercent": false,
       "baseValue": 27.096031,
       "levelAdd": 27.096031,
       "stepValue": 3.387004,
       "maxStep": 2
      },
      {
       "propertyName": "攻击力",
       "propertyIconPath": "133ec725c4ee3c0b046da6e56eab2357dda08baf497ea688c317462fb0b93068",
       "isPercent": false,
       "baseValue": 13.548016,
       "levelAdd": 13.548016,
       "stepValue": 1.693502,
       "maxStep": 2
      },
      {
       "propertyName": "防御力",
       "propertyIconPath": "b0aad49714e2daa2922e1c404f67807aa9b69978ddfc922b721ce5effed76d26",
       "isPercent": false,
       "baseValue": 13.548016,
       "levelAdd": 13.548016,
       "stepValue": 1.693502,
       "maxStep": 2
      },
      {
       "propertyName": "生命值",
       "propertyIconPath": "58021be84b486be322a79b327175328186db239a32bd8880315bddfd1470e8a6",
       "isPercent": true,
       "baseValue": 0.027648,
       "levelAdd": 0.027648,
       "stepValue": 0.0034560005,
       "maxStep": 2
      },
      {
       "propertyName": "攻击力",
       "propertyIconPath": "133ec725c4ee3c0b046da6e56eab2357dda08baf497ea688c317462fb0b93068",
       "isPercent": true,
       "baseValue": 0.027648,
       "levelAdd": 0.027648,
       "stepValue": 0.0034560005,
       "maxStep": 2
      },
      {
       "propertyName": "防御力",
       "propertyIconPath": "b0aad49714e2daa2922e1c404f67807aa9b69978ddfc922b721ce5effed76d26",
       "isPercent": true,
       "baseValue": 0.034560002,
       "levelAdd": 0.034560002,
       "stepValue": 0.0043200003,
       "maxStep": 2
      },
      {
       "propertyName": "速度",
       "propertyIconPath": "5f33a7516d62d6240538ebf9eef7aabde16d97f27eb53e90ae2cf6eef8168feb",
       "isPercent": false,
       "baseValue": 1.6,
       "levelAdd": 1.6,
       "stepValue": 0.2,
       "maxStep": 2
      },
      {
       "propertyName": "暴击率",
       "propertyIconPath": "32af0a785a531bcab9fbe86da7c2f559478bf02bfe8a77d6b539c5702a1a64fb",
       "isPercent": true,
       "baseValue": 0.020736001,
       "levelAdd": 0.020736001,
       "stepValue": 0.0025920009,
       "maxStep": 2
      },
      {
       "propertyName": "暴击伤害",
       "propertyIconPath": "5550e862892998113c65d250603fc60e7a786c520ef82a80f06bd953442418c8",
       "isPercent": true,
       "baseValue": 0.041472,
       "levelAdd": 0.041472,
       "stepValue": 0.0051840004,
       "maxStep": 2
      },
      {
       "propertyName": "效果命中",
       "propertyIconPath": "8198085dc42c26a3e3ce48d55bf1b763c6472ac6251fb2533c710f48ab4a4b46",
       "isPercent": true,
       "baseValue": 0.027648,
       "levelAdd": 0.027648,
       "stepValue": 0.0034560005,
       "maxStep": 2
      },
      {
       "propertyName": "效果抵抗",
       "propertyIconPath": "1663e14dca8f4e42f151ff8d408f9a449e11fe2cacfbb98276eca60c1abafa24",
       "isPercent": true,
       "baseValue": 0.027648,
       "levelAdd": 0.027648,
       "stepValue": 0.0034560005,
       "maxStep": 2
      },
      {
       "propertyName": "击破特攻",
       "propertyIconPath": "757dc56c4923c3e9429fa51fd3d4fa8349581723a44782b0143257fd415bd976",
       "isPercent": true,
       "baseValue": 0.041472,
       "levelAdd": 0.041472,
       "stepValue": 0.0051840004,
       "maxStep": 2
      }
     ]
    },
    "5": {
     "rarity": 5,
     "maxLevel": 15,
     "mainAffixes": [
      {
       "propertyName": "击破特攻",
       "propertyIconPath": "757dc56c4923c3e9429fa51fd3d4fa8349581723a44782b0143257fd415bd976",
       "isPercent": true,
       "baseValue": 0.10368,
       "levelAdd": 0.036288,
       "stepValue": 0,
       "maxStep": 0
      },
      {
       "propertyName": "能量恢复效率",
       "propertyIconPath": "c89104a223ee62a5861a61c20cdb1e42c79d7f6f1767a5dfc5a94f5edbb145ec",
       "isPercent": true,
       "baseValue": 0.031104,
       "levelAdd": 0.010886001,
       "stepValue": 0,
       "maxStep": 0
      },
      {
       "propertyName": "生命值",
       "propertyIconPath": "58021be84b486be322a79b327175328186db239a32bd8880315bddfd1470e8a6",
       "isPercent": true,
       "baseValue": 0.06912,
       "levelAdd": 0.024192,
       "stepValue": 0,
       "maxStep": 0
      },
      {
       "propertyName": "攻击力",
       "propertyIconPath": "133ec725c4ee3c0b046da6e56eab2357dda08baf497ea688c317462fb0b93068",
       "isPercent": true,
       "baseValue": 0.06912,
       "levelAdd": 0.024192,
       "stepValue": 0,
       "maxStep": 0
      },
      {
       "propertyName": "防御力",
       "propertyIconPath": "b0aad49714e2daa2922e1c404f67807aa9b69978ddfc922b721ce5effed76d26",
       "isPercent": true,
       "baseValue": 0.0864,
       "levelAdd": 0.030240001,
       "stepValue": 0,
       "maxStep": 0
      }
     ],
     "subAffixes": [
      {
       "propertyName": "生命值",
       "propertyIconPath": "58021be84b486be322a79b327175328186db239a32bd8880315bddfd1470e8a6",
       "isPercent": false,
       "baseValue": 33.87004,
       "levelAdd": 33.87004,
       "stepValue": 4.233755,
       "maxStep": 2
      },
      {
       "propertyName": "攻击力",
       "propertyIconPath": "133ec725c4ee3c0b046da6e56eab2357dda08baf497ea688c317462fb0b93068",
       "isPercent": false,
       "baseValue": 16.935019,
       "levelAdd": 16.935019,
       "stepValue": 2.116877,
       "maxStep": 2
      },
      {
       "propertyName": "防御力",
       "propertyIconPath": "b0aad49714e2daa2922e1c404f67807aa9b69978ddfc922b721ce5effed76d26",
       "isPercent": false,
       "baseValue": 16.935019,
       "levelAdd": 16.935019,
       "stepValue": 2.116877,
       "maxStep": 2
      },
      {
       "propertyName": "生命值",
       "propertyIconPath": "58021be84b486be322a79b327175328186db239a32bd8880315bddfd1470e8a6",
       "isPercent": true,
       "baseValue": 0.034560002,
       "levelAdd": 0.034560002,
       "stepValue": 0.0043200003,
       "maxStep": 2
      },
      {
       "propertyName": "攻击力",
       "propertyIconPath": "133ec725c4ee3c0b046da6e56eab2357dda08baf497ea688c317462fb0b93068",
       "isPercent": true,
       "baseValue": 0.034560002,
       "levelAdd": 0.034560002,
       "stepValue": 0.0043200003,
       "maxStep": 2
      },
      {
       "propertyName": "防御力",
       "propertyIconPath": "b0aad49714e2daa2922e1c404f67807aa9b69978ddfc922b721ce5effed76d26",
       "isPercent": true,
       "baseValue": 0.0432,
       "levelAdd": 0.0432,
       "stepValue": 0.0054,
       "maxStep": 2
      },
      {
       "propertyName": "速度",
       "propertyIconPath": "5f33a7516d62d6240538ebf9eef7aabde16d97f27eb53e90ae2cf6eef8168feb",
       "isPercent": false,
       "baseValue": 2,
       "levelAdd": 2,
       "stepValue": 0.3,
       "maxStep": 2
      },
      {
       "propertyName": "暴击率",
       "propertyIconPath": "32af0a785a531bcab9fbe86da7c2f559478bf02bfe8a77d6b539c5702a1a64fb",
       "isPercent": true,
       "baseValue": 0.02592,
       "levelAdd": 0.02592,
       "stepValue": 0.0032400002,
       "maxStep": 2
      },
      {
       "propertyName": "暴击伤害",
       "propertyIconPath": "5550e862892998113c65d250603fc60e7a786c520ef82a80f06bd953442418c8",
       "isPercent": true,
       "baseValue": 0.05184,
       "levelAdd": 0.05184,
       "stepValue": 0.0064800004,
       "maxStep": 2
      },
      {
       "propertyName": "效果命中",
       "propertyIconPath": "8198085dc42c26a3e3ce48d55bf1b763c6472ac6251fb2533c710f48ab4a4b46",
       "isPercent": true,
       "baseValue": 0.034560002,
       "levelAdd": 0.034560002,
       "stepValue": 0.0043200003,
       "maxStep": 2
      },
      {
       "propertyName": "效果抵抗",
       "propertyIconPath": "1663e14dca8f4e42f151ff8d408f9a449e11fe2cacfbb98276eca60c1abafa24",
       "isPercent": true,
       "baseValue": 0.034560002,
       "levelAdd": 0.034560002,
       "stepValue": 0.0043200003,
       "maxStep": 2
      },
      {
       "propertyName": "击破特攻",
       "propertyIconPath": "757dc56c4923c3e9429fa51fd3d4fa8349581723a44782b0143257fd415bd976",
       "isPercent": true,
       "baseValue": 0.05184,
       "levelAdd": 0.05184,
       "stepValue": 0.0064800004,
       "maxStep": 2
      }
     ]
    }
   }
  }
 },
 "pageId": "304"
}